lib/__init__.py
lib/colors.py
lib/custom.py
lib/styles.py
colorization-0.1.1.dist-info/LICENSE
colorization-0.1.1.dist-info/METADATA
colorization-0.1.1.dist-info/WHEEL
colorization-0.1.1.dist-info/top_level.txt
colorization-0.1.1.dist-info/RECORD
